dsd-lab/exam/bit6.v
module fulladd(a,b,cin,s,cout);
input a,b,cin;
output s,cout;
assign s = (a^b^cin);
assign cout = ((a&b)|(b&cin)|(cin&a));
endmodule

module bit6(a,b,c,d,e,f,s1,s2,cout1,cout2);
input a,b,c,d,e,f;
output s1,s2,cout1,cout2;
fulladd f1(a,b,c,s1,cout1);
fulladd f2(d,e,f,s2,cout2);
endmodule

dsd-lab/exam/bit6_tb.v
`timescale 1ns/1ns
`include "bit6.v"

module bit6_tb;
reg a,b,c,d,e,f;
wire s1,s2,cout1,cout2;

bit6 b1(a,b,c,d,e,f,s1,s2,cout1,cout2);
initial begin
	$dumpfile("bit6_tb.vcd");
	$dumpvars(0,bit6_tb);
a=0;b=0;c=0;d=0;e=0;f=0;#20;
a=0;b=0;c=0;d=0;e=0;f=1;#20;
a=0;b=0;c=0;d=1;e=1;f=1;#20;
a=0;b=0;c=0;d=0;e=0;f=0;#20;
a=1;b=0;c=1;d=0;e=1;f=1;#20;
a=0;b=0;c=0;d=0;e=0;f=0;#20;
a=0;b=1;c=1;d=1;e=1;f=1;#20;
a=1;b=1;c=1;d=1;e=1;f=1;#20;
$display("Test Complete");
end
endmodule

dsd-lab/exam/bit6_tb.vcd
$date
	Thu Sep 21 10:41:12 2023
$end
$version
	Icarus Verilog
$end
$timescale
	1ns
$end
$scope module bit6_tb $end
$var wire 1 ! s2 $end
$var wire 1 " s1 $end
$var wire 1 # cout2 $end
$var wire 1 $ cout1 $end
$var reg 1 % a $end
$var reg 1 & b $end
$var reg 1 ' c $end
$var reg 1 ( d $end
$var reg 1 ) e $end
$var reg 1 * f $end
$scope module b1 $end
$var wire 1 % a $end
$var wire 1 & b $end
$var wire 1 ' c $end
$var wire 1 ( d $end
$var wire 1 ) e $end
$var wire 1 * f $end
$var wire 1 ! s2 $end
$var wire 1 " s1 $end
$var wire 1 # cout2 $end
$var wire 1 $ cout1 $end
$scope module f1 $end
$var wire 1 % a $end
$var wire 1 & b $end
$var wire 1 ' cin $end
$var wire 1 $ cout $end
$var wire 1 " s $end
$upscope $end
$scope module f2 $end
$var wire 1 ( a $end
$var wire 1 ) b $end
$var wire 1 * cin $end
$var wire 1 # cout $end
$var wire 1 ! s $end
$upscope $end
$upscope $end
$upscope $end
$enddefinitions $end
#0
$dumpvars
0*
0)
0(
0'
0&
0%
0$
0#
0"
0!
$end
#20
1!
1*
#40
1#
1)
1(
#60
0#
0!
0*
0)
0(
#80
1#
1$
1*
1)
1'
1%
#100
0#
0$
0*
0)
0'
0%
#120
1$
1#
1!
1*
1)
1(
1'
1&
#140
1"
1%
