dsd-lab/Lab-4/Q4/Encoder16_4.v
module Encoder16_4(w, y, z);
    input [15:0] w;
    output reg [3:0] y;
    output reg z;
    integer k;

    always @(*)
    begin
        y = 4'b0000;
        z = 1;
        if (w == 0)
        begin
            z = 0;
            y = 4'bXXXX;
        end
        else
        begin
            for (k = 0; k <= 15; k = k + 1)
            begin
                if (w[k] == 1)
                begin
                    y = k;
                end
            end
        end
    end
endmodule

Week-6/Q4/Encoder16_4_tb.v
`timescale 1ns/1ns
`include "Encoder16_4.v"

module Encoder16_4_tb();
    reg [15:0] w;
    wire [3:0] y;
    wire z;

    Encoder16_4 q(w, y, z);

    initial begin
        $dumpfile("Encoder16_4_tb.vcd");
        $dumpvars(0, Encoder16_4_tb);

        w = 16'b0000000000000000; 
        #20;
        
        w = 16'b0000000000000001; 
        #20;

	w = 16'b0000000000000010; 
        #20;
        
        w = 16'b0000000000000011; 
        #20;
        
        w = 16'b0000000000000100; 
        #20;
        
        w = 16'b0000000000000101; 
        #20;
        
        w = 16'b0000000000000110; 
        #20;
        
        w = 16'b0000000000000111; 
        #20;
        
        w = 16'b0000000000001000; 
        #20;
        
        w = 16'b0000000000001001; 
        #20;
        
        w = 16'b0000000000001010; 
        #20;
        
        w = 16'b0000000000001011; 
        #20;
        
        w = 16'b0000000000001100; 
        #20;
        
        w = 16'b0000000000001101; 
        #20;
        
        w = 16'b0000000000001110; 
        #20;
        
        w = 16'b0000000000001111; 
        #20;


        $display("Test Complete");
        $finish;
    end
endmodule

dsd-lab/Lab-4/Q4/Encoder16_4_tb.vcd
$date
	Thu Aug 31 11:00:15 2023
$end
$version
	Icarus Verilog
$end
$timescale
	1ns
$end
$scope module Encoder16_4_tb $end
$var wire 1 ! z $end
$var wire 4 " y [3:0] $end
$var reg 16 # w [15:0] $end
$scope module q $end
$var wire 16 $ w [15:0] $end
$var reg 4 % y [3:0] $end
$var reg 1 ! z $end
$var integer 32 & k [31:0] $end
$upscope $end
$upscope $end
$enddefinitions $end
#0
$dumpvars
bx &
bx %
b0 $
b0 #
bx "
0!
$end
#20
b10000 &
1!
b0 "
b0 %
b1 #
b1 $
#40
b1 "
b1 %
b10000 &
b10 #
b10 $
#60
b10000 &
b1 "
b1 %
b11 #
b11 $
#80
b10000 &
b10 "
b10 %
b100 #
b100 $
#100
b10000 &
b10 "
b10 %
b101 #
b101 $
#120
b10000 &
b10 "
b10 %
b110 #
b110 $
#140
b10000 &
b10 "
b10 %
b111 #
b111 $
#160
b10000 &
b11 "
b11 %
b1000 #
b1000 $
#180
b10000 &
b11 "
b11 %
b1001 #
b1001 $
#200
b10000 &
b11 "
b11 %
b1010 #
b1010 $
#220
b10000 &
b11 "
b11 %
b1011 #
b1011 $
#240
b10000 &
b11 "
b11 %
b1100 #
b1100 $
#260
b10000 &
b11 "
b11 %
b1101 #
b1101 $
#280
b10000 &
b11 "
b11 %
b1110 #
b1110 $
#300
b10000 &
b11 "
b11 %
b1111 #
b1111 $
