dsd-lab/Lab-10/Q3/tFlipFlop.v
module tFlipFlop(t,clk,reset,q);
input t,clk,reset;
output reg q;
always@(posedge clk)
begin
if(t)
q<=~q;
end
always@(reset)
begin
if(reset)
q<=0;
end
endmodule

dsd-lab/Lab-10/Q3/Q3.v
`include "tFlipFlop.v"
module Q3(reset,clk,V);
input reset,clk;
output [2:0]V;

tFlipFlop t1((V[2]^V[1]),clk,reset,V[2]);
tFlipFlop t2((V[1]^V[0]),clk,reset,V[1]);
tFlipFlop t3(~(V[2]^V[0]),clk,reset,V[0]);

endmodule

dsd-lab/Lab-10/Q3/Q3_tb.v
`timescale 1ns/1ns
`include "Q3.v"
module Q3_tb;
reg clk,reset;
wire [2:0]V;
Q3 Q(reset,clk,V);
always #10 clk=~clk;
initial begin
$dumpfile("Q3_tb.vcd");
$dumpvars(0,Q3_tb);
clk=0;
end
initial begin
reset=1'b1;#20;
reset=1'b0;#20;
reset=1'b0;#20;
reset=1'b0;#20;
reset=1'b0;#20;
reset=1'b0;#20;
reset=1'b0;#20;
reset=1'b0;#20;
reset=1'b0;#20;
reset=1'b0;#20;
$finish;
end
endmodule

dsd-lab/Lab-10/Q3/Q3_tb.vcd
$date
	Thu Nov  2 10:54:55 2023
$end
$version
	Icarus Verilog
$end
$timescale
	1ns
$end
$scope module Q3_tb $end
$var wire 3 ! V [2:0] $end
$var reg 1 " clk $end
$var reg 1 # reset $end
$scope module Q $end
$var wire 1 " clk $end
$var wire 1 # reset $end
$var wire 3 $ V [2:0] $end
$scope module t1 $end
$var wire 1 " clk $end
$var wire 1 # reset $end
$var wire 1 % t $end
$var reg 1 & q $end
$upscope $end
$scope module t2 $end
$var wire 1 " clk $end
$var wire 1 # reset $end
$var wire 1 ' t $end
$var reg 1 ( q $end
$upscope $end
$scope module t3 $end
$var wire 1 " clk $end
$var wire 1 # reset $end
$var wire 1 ) t $end
$var reg 1 * q $end
$upscope $end
$upscope $end
$upscope $end
$enddefinitions $end
#0
$dumpvars
0*
1)
0(
0'
0&
0%
b0 $
1#
0"
b0 !
$end
#10
0)
1'
b1 !
b1 $
1*
1"
#20
0"
0#
#30
0'
1%
b11 !
b11 $
1(
1"
#40
0"
#50
1)
0%
b111 !
b111 $
1&
1"
#60
0"
#70
0)
1'
b110 !
b110 $
0*
1"
#80
0"
#90
0'
1%
b100 !
b100 $
0(
1"
#100
0"
#110
1)
0%
b0 !
b0 $
0&
1"
#120
0"
#130
0)
1'
b1 !
b1 $
1*
1"
#140
0"
#150
0'
1%
b11 !
b11 $
1(
1"
#160
0"
#170
1)
0%
b111 !
b111 $
1&
1"
#180
0"
#190
0)
1'
b110 !
b110 $
0*
1"
