dsd-lab/Week-4/grtobin.v
module grtobin(G,B);
parameter n = 8;
input [n-1:0]G;
output reg [n-1:0]B;
integer i;
always @ (G)
begin 
	B[n-1] = G[n-1];
	for (i=n-2;i>=0;i--)
		begin
		B[i] = B[i+1] ^ G[i];
		end
	end
endmodule

dsd-lab/Week-4/grtobin_tb.v
`timescale 1ns/1ns
`include "grtobin.v"

module grtobin_tb;
parameter n=8;
reg [n-1:0]G;
wire [n-1:0]B;

grtobin h1(G,B);
initial begin
	
		$dumpfile("grtobin_tb.vcd");
		$dumpvars(0,grtobin_tb);
		
G = 4'b 0000;
#20;

G = 4'b 0001;
#20;

G = 4'b 0010;
#20; 

G = 4'b 0011; 
#20;

G = 4'b 0100;
#20;

G = 4'b 0101;
#20;

G = 4'b 0110;
#20;

G = 4'b 0111;
#20;

G = 4'b 1000;
#20;

G = 4'b 1001;
#20;

G = 4'b 1010;
#20;

G = 4'b 1011;
#20;

G = 4'b 1100;
#20;

G = 4'b 1101;
#20;

G = 4'b 1110;
#20;

G = 4'b 1111;
#20;

	$display("Test Complete");
	
end
endmodule

dsd-lab/Lab-3/grtobin_tb.vcd
$date
	Thu Aug 24 11:23:14 2023
$end
$version
	Icarus Verilog
$end
$timescale
	1ns
$end
$scope module grtobin_tb $end
$var wire 8 ! B [7:0] $end
$var reg 8 " G [7:0] $end
$scope module h1 $end
$var wire 8 # G [7:0] $end
$var reg 8 $ B [7:0] $end
$var integer 32 % i [31:0] $end
$upscope $end
$upscope $end
$enddefinitions $end
#0
$dumpvars
b11111111111111111111111111111111 %
b0 $
b0 #
b0 "
b0 !
$end
#20
b1 !
b1 $
b11111111111111111111111111111111 %
b1 "
b1 #
#40
b11 !
b11 $
b11111111111111111111111111111111 %
b10 "
b10 #
#60
b10 !
b10 $
b11111111111111111111111111111111 %
b11 "
b11 #
#80
b111 !
b111 $
b11111111111111111111111111111111 %
b100 "
b100 #
#100
b110 !
b110 $
b11111111111111111111111111111111 %
b101 "
b101 #
#120
b100 !
b100 $
b11111111111111111111111111111111 %
b110 "
b110 #
#140
b101 !
b101 $
b11111111111111111111111111111111 %
b111 "
b111 #
#160
b1111 !
b1111 $
b11111111111111111111111111111111 %
b1000 "
b1000 #
#180
b1110 !
b1110 $
b11111111111111111111111111111111 %
b1001 "
b1001 #
#200
b1100 !
b1100 $
b11111111111111111111111111111111 %
b1010 "
b1010 #
#220
b1101 !
b1101 $
b11111111111111111111111111111111 %
b1011 "
b1011 #
#240
b1000 !
b1000 $
b11111111111111111111111111111111 %
b1100 "
b1100 #
#260
b1001 !
b1001 $
b11111111111111111111111111111111 %
b1101 "
b1101 #
#280
b1011 !
b1011 $
b11111111111111111111111111111111 %
b1110 "
b1110 #
#300
b1010 !
b1010 $
b11111111111111111111111111111111 %
b1111 "
b1111 #
