dsd-lab/Week-4/mux4.v
module mux4(S,W,f);
input [1:0]S;
input[3:0]W;
output reg f;
always @ (S|W)
begin
if (S==0)
f = W[0];
else if (S==1)
f = W[1];
else if (S==2)
f = W[2];
else
f = W[3];
end
endmodule

dsd-lab/Lab-3/mux4_tb.v
`timescale 1ns/1ns
`include "mux4.v"

module mux4_tb;
reg[1:0]S;
reg[3:0]W;
wire f;

mux4 h1(S,W,f);
initial begin

        $dumpfile("mux4_tb.vcd");
        $dumpvars(0,mux4_tb);

	S=0;
	W=4'b 1110;
	#20

	S=1;
	W=4'b 0011;
	#20

	S=2;
	W=4'b 0111;
	#20

	S=3;
	W=4'b 0100;
	#20

	S=0;
	W=4'b 0001;
	#20

	S=1;
	W=4'b 0101;
	#20

	S=2;
	W=4'b 1010;
	#20

	S=3;
	W=4'b 1001;
	#20

	$display("Test Complete");

end
endmodule

dsd-lab/Lab-3/mux4_tb.vcd
$date
	Thu Aug 24 09:46:10 2023
$end
$version
	Icarus Verilog
$end
$timescale
	1ns
$end
$scope module mux4_tb $end
$var wire 1 ! f $end
$var reg 2 " S [1:0] $end
$var reg 4 # W [3:0] $end
$scope module h1 $end
$var wire 2 $ S [1:0] $end
$var wire 4 % W [3:0] $end
$var reg 1 ! f $end
$upscope $end
$upscope $end
$enddefinitions $end
#0
$dumpvars
b1110 %
b0 $
b1110 #
b0 "
0!
$end
#20
1!
b11 #
b11 %
b1 "
b1 $
#40
b111 #
b111 %
b10 "
b10 $
#60
b100 #
b100 %
b11 "
b11 $
#80
b1 #
b1 %
b0 "
b0 $
#100
0!
b101 #
b101 %
b1 "
b1 $
#120
b1010 #
b1010 %
b10 "
b10 $
#140
1!
b1001 #
b1001 %
b11 "
b11 $
