dsd-lab/Lab-10/Q2/srFlipFlop.v
module srFlipFlop(s,r,clk,reset,q);
input s,r,clk,reset;
output reg q;

always@(posedge clk)
begin

if(s==1&r==0)
q<=1;
else if(s==0&r==1)
q<=0;
end

always@(reset)
begin
if(reset)
q<=0;
end

endmodule

dsd-lab/Lab-10/Q2/Q2.v
`include "srFlipFlop.v"
module Q2(reset,clk,V);
input reset,clk;
output [2:0]V;

srFlipFlop sr1(((~V[1])&(~V[0])),(V[2]&(~V[1])),clk,reset,V[2]);
srFlipFlop sr2(((~V[2])&(~V[1])),((V[2]&(~V[0]))|((~V[2])&V[1]&V[0])),clk,reset,V[1]);
srFlipFlop sr3((~V[0]),(V[0]&((~V[2])|V[1])),clk,reset,V[0]);

endmodule

dsd-lab/Lab-10/Q2/Q2_tb.v
`timescale 1ns/1ns
`include "Q2.v"
module Q2_tb;
reg clk,reset;
wire [2:0]V;
Q2 Q(reset,clk,V);
always #10 clk=~clk;
initial begin
$dumpfile("Q2_tb.vcd");
$dumpvars(0,Q2_tb);
clk=0;
end
initial begin
reset=1'b1;#20;
reset=1'b0;#20;
reset=1'b0;#20;
reset=1'b0;#20;
reset=1'b0;#20;
reset=1'b0;#20;
reset=1'b0;#20;
reset=1'b0;#20;
reset=1'b0;#20;
reset=1'b0;#20;
$finish;
end
endmodule

dsd-lab/Lab-10/Q2/Q2_tb.vcd
$date
	Thu Nov  2 10:33:03 2023
$end
$version
	Icarus Verilog
$end
$timescale
	1ns
$end
$scope module Q2_tb $end
$var wire 3 ! V [2:0] $end
$var reg 1 " clk $end
$var reg 1 # reset $end
$scope module Q $end
$var wire 1 " clk $end
$var wire 1 # reset $end
$var wire 3 $ V [2:0] $end
$scope module sr1 $end
$var wire 1 " clk $end
$var wire 1 % r $end
$var wire 1 # reset $end
$var wire 1 & s $end
$var reg 1 ' q $end
$upscope $end
$scope module sr2 $end
$var wire 1 " clk $end
$var wire 1 ( r $end
$var wire 1 # reset $end
$var wire 1 ) s $end
$var reg 1 * q $end
$upscope $end
$scope module sr3 $end
$var wire 1 " clk $end
$var wire 1 + r $end
$var wire 1 # reset $end
$var wire 1 , s $end
$var reg 1 - q $end
$upscope $end
$upscope $end
$upscope $end
$enddefinitions $end
#0
$dumpvars
0-
1,
0+
0*
1)
0(
0'
1&
0%
b0 $
1#
0"
b0 !
$end
#10
0(
0)
0&
1+
0,
1'
1*
b111 !
b111 $
1-
1"
#20
0"
0#
#30
1(
0+
1,
b110 !
b110 $
0-
1"
#40
0"
#50
0(
1%
0+
0,
0*
b101 !
b101 $
1-
1"
#60
0"
#70
1+
1)
0%
b1 !
b1 $
0'
1"
#80
0"
#90
0)
0+
1,
1*
b10 !
b10 $
0-
1"
#100
0"
#110
1(
1+
0,
b11 !
b11 $
1-
1"
#120
0"
#130
1)
0(
1&
0+
1,
0*
b0 !
b0 $
0-
1"
#140
0"
#150
0&
0(
0)
1+
0,
0%
1-
1*
b111 !
b111 $
1'
1"
#160
0"
#170
1(
0+
1,
b110 !
b110 $
0-
1"
#180
0"
#190
0(
1%
0,
1-
b101 !
b101 $
0*
1"
