dsd-lab/Lab-1/q1a/q1a.v
module q1a(a,b,c,d,f);
input a,b,c,d;
output f;
assign f=c|(a&d);
endmodule

dsd-lab/Week-2/q1a/q1a_tb.v
`timescale 1ns/1ns
`include "q1a.v"
module q1a_tb;
reg a,b,c,d;
wire f;
q1a q1a1(a,b,c,d,f);
initial begin
	$dumpfile("q1a_tb.vcd");
	$dumpvars(0,q1a_tb);
	a=0;
	b=0;
	c=0;
	d=0;
	#5; 
	a=0;
	b=0;
	c=0;
	d=1;
	#5; 
	a=0;
	b=0;
	c=1;
	d=0;
	#5; 
	a=0;
	b=0;
	c=1;
	d=1;
	#5; 
	a=0;
	b=1;
	c=0;
	d=0;
	#5; 
	a=0;
	b=1;
	c=0;
	d=1;
	#5; 
	a=0;
	b=1;
	c=1;
	d=0;
	#5; 
	a=0;
	b=1;
	c=1;
	d=1;
	#5; 
	a=1;
	b=0;
	c=0;
	d=0;
	#5; 
	a=1;
	b=0;
	c=0;
	d=1;
	#5; 
	a=1;
	b=0;
	c=1;
	d=0;
	#5; 
	a=1;
	b=0;
	c=1;
	d=1;
	#5; 
	a=1;
	b=1;
	c=0;
	d=0;
	#5; 
	a=1;
	b=1;
	c=0;
	d=1;
	#5; 
	a=1;
	b=1;
	c=1;
	d=0;
	#5; 
	a=1;
	b=1;
	c=1;
	d=1;
	#5;
	$display("Test Completed");
end
endmodule

dsd-lab/Lab-1/q1a/q1a_tb.vcd
$date
	Thu Aug 10 10:16:32 2023
$end
$version
	Icarus Verilog
$end
$timescale
	1ns
$end
$scope module q1a_tb $end
$var wire 1 ! f $end
$var reg 1 " a $end
$var reg 1 # b $end
$var reg 1 $ c $end
$var reg 1 % d $end
$scope module q1a1 $end
$var wire 1 " a $end
$var wire 1 # b $end
$var wire 1 $ c $end
$var wire 1 % d $end
$var wire 1 ! f $end
$upscope $end
$upscope $end
$enddefinitions $end
#0
$dumpvars
0%
0$
0#
0"
0!
$end
#5
1%
#10
1!
0%
1$
#15
1%
#20
0!
0%
0$
1#
#25
1%
#30
1!
0%
1$
#35
1%
#40
0!
0%
0$
0#
1"
#45
1!
1%
#50
0%
1$
#55
1%
#60
0!
0%
0$
1#
#65
1!
1%
#70
0%
1$
#75
1%
