dsd-lab/Lab-5/Q3/lab5q3.v
module dec4to16(w, en, y);
   input [3:0]w;
   input en;
   output reg [0:15]y;
   integer k;
   
   always @ (w or en)
      for (k=0;k<=15;k++)
         if ((w==k) && (en==1))
            	y[k] = 1;
         else 
        	y[k] = 0;
endmodule

 module lab5q3 (w,f);
    input [3:0]w;
    wire [0:15]y;
    output f;
    dec4to16 stg0(w[3:0], 1'b1, y[0:15]);
    assign f = {y[1], y[4], y[6], y[8], y[9], y[13], y[15]};
 endmodule

dsd-lab/Lab-5/Q3/lab5q3_tb.v
`timescale 1ns/1ns
`include "lab5q3.v"

module lab5q3_tb;
  reg [3:0]w;
  wire f;

  lab5q3 l1(w,f);
  initial begin
        $dumpfile("lab5q3_tb.vcd");
        $dumpvars(0, lab5q3_tb);

w = 4'b 0000;
#20;

w = 4'b 0001;
#20;

w = 4'b 0010;
#20; 

w = 4'b 0011; 
#20;

w = 4'b 0100;
#20;

w = 4'b 0101;
#20;

w = 4'b 0110;
#20;

w = 4'b 0111;
#20;

w = 4'b 1000;
#20;

w = 4'b 1001;
#20;

w = 4'b 1010;
#20;

w = 4'b 1011;
#20;

w = 4'b 1100;
#20;

w = 4'b 1101;
#20;

w = 4'b 1110;
#20;

w = 4'b 1111;
#20;

    
    $display ("Test Complete");
    $finish; 
  end
endmodule

dsd-lab/Lab-5/Q3/lab5q3_tb.vcd
$date
	Thu Sep 14 09:56:29 2023
$end
$version
	Icarus Verilog
$end
$timescale
	1ns
$end
$scope module lab5q3_tb $end
$var wire 1 ! f $end
$var reg 4 " w [3:0] $end
$scope module l1 $end
$var wire 4 # w [3:0] $end
$var wire 16 $ y [0:15] $end
$var wire 1 ! f $end
$scope module stg0 $end
$var wire 1 % en $end
$var wire 4 & w [3:0] $end
$var reg 16 ' y [0:15] $end
$var integer 32 ( k [31:0] $end
$upscope $end
$upscope $end
$upscope $end
$enddefinitions $end
#0
$dumpvars
b10000 (
b1000000000000000 '
b0 &
1%
b1000000000000000 $
b0 #
b0 "
0!
$end
#20
b100000000000000 $
b100000000000000 '
b10000 (
b1 "
b1 #
b1 &
#40
b10000000000000 $
b10000000000000 '
b10000 (
b10 "
b10 #
b10 &
#60
b1000000000000 $
b1000000000000 '
b10000 (
b11 "
b11 #
b11 &
#80
b100000000000 $
b100000000000 '
b10000 (
b100 "
b100 #
b100 &
#100
b10000000000 $
b10000000000 '
b10000 (
b101 "
b101 #
b101 &
#120
b1000000000 $
b1000000000 '
b10000 (
b110 "
b110 #
b110 &
#140
b100000000 $
b100000000 '
b10000 (
b111 "
b111 #
b111 &
#160
b10000000 $
b10000000 '
b10000 (
b1000 "
b1000 #
b1000 &
#180
b1000000 $
b1000000 '
b10000 (
b1001 "
b1001 #
b1001 &
#200
b100000 $
b100000 '
b10000 (
b1010 "
b1010 #
b1010 &
#220
b10000 $
b10000 '
b10000 (
b1011 "
b1011 #
b1011 &
#240
b1000 $
b1000 '
b10000 (
b1100 "
b1100 #
b1100 &
#260
b100 $
b100 '
b10000 (
b1101 "
b1101 #
b1101 &
#280
b10 $
b10 '
b10000 (
b1110 "
b1110 #
b1110 &
#300
1!
b1 $
b1 '
b10000 (
b1111 "
b1111 #
b1111 &
