dsd-lab/Lab-6/Q4/srFlipFlop.v
module srFlipFlop(s,r,clk,reset,q);
input s,r,clk,reset;
output reg q;
always@(negedge clk)
begin
if(!reset)
q<=0;
else if(s==1&r==0)
q<=1;
else if(s==0&r==1)
q<=0;
end
endmodule

dsd-lab/Lab-6/Q4/srFlipFlop_tb.v
`timescale 1ns/1ns
`include "srFlipFlop.v"
module srFlipFlop_tb;
reg s,r,clk,reset;
wire q;
srFlipFlop sff(s,r,clk,reset,q);
always #10 clk=~clk;
initial begin
$dumpfile("srFlipFlop_tb.vcd");
$dumpvars(0,srFlipFlop_tb);
clk=0;
#100 $finish;
end
initial begin
s=0;r=0;reset=0;#10;
s=0;r=0;reset=1;#20;
s=1;r=0;reset=1;#20;
s=0;r=1;reset=1;#20;
s=0;r=0;reset=0;#20;
s=0;r=0;reset=1;#10;
end
endmodule

dsd-lab/Lab-6/Q4/srFlipFlop_tb.vcd
$date
	Thu Oct  5 10:57:09 2023
$end
$version
	Icarus Verilog
$end
$timescale
	1ns
$end
$scope module srFlipFlop_tb $end
$var wire 1 ! q $end
$var reg 1 " clk $end
$var reg 1 # r $end
$var reg 1 $ reset $end
$var reg 1 % s $end
$scope module sff $end
$var wire 1 " clk $end
$var wire 1 # r $end
$var wire 1 $ reset $end
$var wire 1 % s $end
$var reg 1 ! q $end
$upscope $end
$upscope $end
$enddefinitions $end
#0
$dumpvars
0%
0$
0#
0"
0!
$end
#10
1$
1"
#20
0"
#30
1"
1%
#40
1!
0"
#50
1"
1#
0%
#60
0!
0"
#70
1"
0$
0#
#80
0"
#90
1"
1$
