dsd-lab/Lab-7/Q2/q2.v
module q2(i,clk,q);
parameter n = 8;
input [n-1:0]i;
input clk;
output reg [n-1:0]q;
always @ (posedge clk)
	q<=i;
endmodule

dsd-lab/Lab-7/Q2/q2_tb.v
`timescale 1ns/1ns
`include "q2.v"

module q2_tb;
	parameter n=8;
	reg [n-1:0]i;
	reg clk;
	wire [n-1:0]q;
q2 stage0(i,clk,q);

initial begin
	$dumpfile("q2_tb.vcd");
	$dumpvars(0,q2_tb);
	clk = 0;
	forever #10 clk = ~clk;
end
initial begin
	i=8'b 10101010;#20;
	i=8'b 01010101;#20;
	i=8'b 11101010;#20;
	i=8'b 01011111;#20;
	i=8'b 00000000;#20;
	i=8'b 01111100;#20;
	i=8'b 10000000;#20;
	i=8'b 00010001;#20;
	
	$display("Test Complete");
	$finish;
	
end
endmodule

dsd-lab/Lab-7/Q2/q2_tb.vcd
$date
	Wed Oct 11 17:31:14 2023
$end
$version
	Icarus Verilog
$end
$timescale
	1ns
$end
$scope module q2_tb $end
$var wire 8 ! q [7:0] $end
$var reg 1 " clk $end
$var reg 8 # i [7:0] $end
$scope module stage0 $end
$var wire 1 " clk $end
$var wire 8 $ i [7:0] $end
$var reg 8 % q [7:0] $end
$upscope $end
$upscope $end
$enddefinitions $end
#0
$dumpvars
bx %
b10101010 $
b10101010 #
0"
bx !
$end
#10
b10101010 !
b10101010 %
1"
#20
0"
b1010101 #
b1010101 $
#30
b1010101 !
b1010101 %
1"
#40
0"
b11101010 #
b11101010 $
#50
b11101010 !
b11101010 %
1"
#60
0"
b1011111 #
b1011111 $
#70
b1011111 !
b1011111 %
1"
#80
0"
b0 #
b0 $
#90
b0 !
b0 %
1"
#100
0"
b1111100 #
b1111100 $
#110
b1111100 !
b1111100 %
1"
#120
0"
b10000000 #
b10000000 $
#130
b10000000 !
b10000000 %
1"
#140
0"
b10001 #
b10001 $
#150
b10001 !
b10001 %
1"
