dsd-lab/Lab-1/q2b/q2b.v
module q2b                                              (a,b,c,d,f);
input a,b,c,d;
output f;
assign f=(~c|d) & (~a|d) & (a|~b|~c|~d);
endmodule

dsd-lab/Week-2/q2b/q2b_tb.v
`timescale 1ns/1ns
`include "q2b.v"
module q2b_tb;
reg a,b,c,d;
wire f;
q2b q2b1(a,b,c,d,f);
initial begin
	$dumpfile("q2b_tb.vcd");
	$dumpvars(0,q2b_tb);
	a=0;
	b=0;
	c=0;
	d=0;
	#5; 
	a=0;
	b=0;
	c=0;
	d=1;
	#5; 
	a=0;
	b=0;
	c=1;
	d=0;
	#5; 
	a=0;
	b=0;
	c=1;
	d=1;
	#5; 
	a=0;
	b=1;
	c=0;
	d=0;
	#5; 
	a=0;
	b=1;
	c=0;
	d=1;
	#5; 
	a=0;
	b=1;
	c=1;
	d=0;
	#5; 
	a=0;
	b=1;
	c=1;
	d=1;
	#5; 
	a=1;
	b=0;
	c=0;
	d=0;
	#5; 
	a=1;
	b=0;
	c=0;
	d=1;
	#5; 
	a=1;
	b=0;
	c=1;
	d=0;
	#5; 
	a=1;
	b=0;
	c=1;
	d=1;
	#5; 
	a=1;
	b=1;
	c=0;
	d=0;
	#5; 
	a=1;
	b=1;
	c=0;
	d=1;
	#5; 
	a=1;
	b=1;
	c=1;
	d=0;
	#5; 
	a=1;
	b=1;
	c=1;
	d=1;
	#5;
	$display("Test Completed");
end
endmodule

dsd-lab/Lab-1/q2b/q2b_tb.vcd
$date
	Thu Aug 10 11:14:47 2023
$end
$version
	Icarus Verilog
$end
$timescale
	1ns
$end
$scope module q2b_tb $end
$var wire 1 ! f $end
$var reg 1 " a $end
$var reg 1 # b $end
$var reg 1 $ c $end
$var reg 1 % d $end
$scope module q2b1 $end
$var wire 1 " a $end
$var wire 1 # b $end
$var wire 1 $ c $end
$var wire 1 % d $end
$var wire 1 ! f $end
$upscope $end
$upscope $end
$enddefinitions $end
#0
$dumpvars
0%
0$
0#
0"
1!
$end
#5
1%
#10
0!
0%
1$
#15
1!
1%
#20
0%
0$
1#
#25
1%
#30
0!
0%
1$
#35
1%
#40
0%
0$
0#
1"
#45
1!
1%
#50
0!
0%
1$
#55
1!
1%
#60
0!
0%
0$
1#
#65
1!
1%
#70
0!
0%
1$
#75
1!
1%
