dsd-lab/Week-1/example1.v
module example1(x1,x2,x3,f);
	input x1,x2,x3;
	output f;
	and(g,x1,x2);
	not(k,x2);
	and(h,k,x3);
	or(f,g,h);
endmodule

dsd-lab/Lab-0/example1_tb.v
`timescale 1ns/1ns
`include "example1.v"

module example1_tb;
reg a,b,c;
wire d;

example1 e1(a,b,c,d);
initial begin

	$dumpfile("example1_tb.vcd");
	$dumpvars(0, example1_tb);
	
	a=0;
	b=0;
	c=0;
	#20;
	
	a=0;
	b=0;
	c=1;
	#20;
	
	a=0;
	b=1;
	c=0;
	#20;
	
	a=0;
	b=1;
	c=1;
	#20;
	
	a=1;
	b=0;
	c=0;
	#20;
	
	a=1;
	b=0;
	c=1;
	#20;
	
	a=1;
	b=1;
	c=0;
	#20;
	
	a=1;
	b=1;
	c=1;
	#20;
	
	$display("Test complete");
end 

endmodule

dsd-lab/Week-1/example1_tb.vcd
$date
	Thu Aug  3 10:39:54 2023
$end
$version
	Icarus Verilog
$end
$timescale
	1ns
$end
$scope module example1_tb $end
$var wire 1 ! d $end
$var reg 1 " a $end
$var reg 1 # b $end
$var reg 1 $ c $end
$scope module e1 $end
$var wire 1 ! f $end
$var wire 1 % g $end
$var wire 1 & h $end
$var wire 1 ' k $end
$var wire 1 " x1 $end
$var wire 1 # x2 $end
$var wire 1 $ x3 $end
$upscope $end
$upscope $end
$enddefinitions $end
#0
$dumpvars
1'
0&
0%
0$
0#
0"
0!
$end
#20
1!
1&
1$
#40
0!
0&
0'
0$
1#
#60
1$
#80
1'
0$
0#
1"
#100
1!
1&
1$
#120
0&
1%
0'
0$
1#
#140
1$
