dsd-lab/Lab-6/Q3/jkFlipFlop.v
module jkFlipFlop(j,k,clk,reset,q);
input j,k,clk,reset;
output reg q;
always@(posedge clk)
begin
if(reset)
q<=0;
else if(k==1&j==1)
q<=~q;
else if(k==1)
q<=0;
else if(j==1)
q<=1;
end
endmodule

dsd-lab/Lab-6/Q3/jkFlipFlop_tb.v
`timescale 1ns/1ns
`include "jkFlipFlop.v"
module jkFlipFlop_tb;
reg j,k,clk,reset;
wire q;
jkFlipFlop jkFF(j,k,clk,reset,q);
always #10 clk=~clk;
initial begin
$dumpfile("jkFlipFlop_tb.vcd");
$dumpvars(0,jkFlipFlop_tb);
clk=1;
#120 $finish;
end
initial begin
j=0;k=0;reset=1;#10;
j=0;k=0;reset=0;#20;
j=1;k=0;reset=0;#20;
j=0;k=1;reset=0;#20;
j=1;k=1;reset=0;#20;
j=0;k=0;reset=1;#20;
j=0;k=0;reset=0;#10;
end
endmodule

dsd-lab/Lab-6/Q3/jkFlipFlop_tb.vcd
$date
	Thu Oct  5 10:45:59 2023
$end
$version
	Icarus Verilog
$end
$timescale
	1ns
$end
$scope module jkFlipFlop_tb $end
$var wire 1 ! q $end
$var reg 1 " clk $end
$var reg 1 # j $end
$var reg 1 $ k $end
$var reg 1 % reset $end
$scope module jkFF $end
$var wire 1 " clk $end
$var wire 1 # j $end
$var wire 1 $ k $end
$var wire 1 % reset $end
$var reg 1 ! q $end
$upscope $end
$upscope $end
$enddefinitions $end
#0
$dumpvars
1%
0$
0#
1"
0!
$end
#10
0%
0"
#20
1"
#30
0"
1#
#40
1!
1"
#50
0"
1$
0#
#60
0!
1"
#70
0"
1#
#80
1!
1"
#90
0"
1%
0$
0#
#100
0!
1"
#110
0"
0%
