dsd-lab/Lab-4/Q3-b/Encoder4_2.v
module Encoder4_2(w, y, z);
   input [3:0]w;
   output reg [1:0]y;
   output reg z;
   
   always @*
   begin
   z=1;
   casex(w)
     4'b1XXX: y=3;
     4'b01XX: y=2;
     4'b001X: y=1;
     4'b0001: y=0;
     default:
     	     begin
     	     	z=0;
     	     	y=2'bXX;
     	     end
    endcase
    end
endmodule

dsd-lab/Week-5/Q3/Encoder4_2_tb.v
`timescale 1ns/1ns
`include "Encoder4_2.v"

module Encoder4_2_tb;
  reg [3:0]w;
  wire [1:0]y;
  wire z;   
integer i;

Encoder4_2 E1(w, y, z);
  initial begin
    $dumpfile("Encoder4_2_tb.vcd");
    $dumpvars(0, Encoder4_2_tb);

    for(i=0;i<15;i=i+1)
    begin
    w=i;
    #10;
    end

    $display ("Test Complete");
    $finish; 
  end
endmodule

dsd-lab/Lab-4/Q3/Encoder4_2_tb.vcd
$date
	Thu Aug 31 10:13:53 2023
$end
$version
	Icarus Verilog
$end
$timescale
	1ns
$end
$scope module Encoder4_2_tb $end
$var wire 1 ! z $end
$var wire 2 " y [1:0] $end
$var reg 4 # w [3:0] $end
$var integer 32 $ i [31:0] $end
$scope module E1 $end
$var wire 4 % w [3:0] $end
$var reg 2 & y [1:0] $end
$var reg 1 ! z $end
$upscope $end
$upscope $end
$enddefinitions $end
#0
$dumpvars
b0 &
b0 %
b0 $
b0 #
b0 "
0!
$end
#10
1!
b1 #
b1 %
b1 $
#20
b1 "
b1 &
b10 #
b10 %
b10 $
#30
b11 #
b11 %
b11 $
#40
b10 "
b10 &
b100 #
b100 %
b100 $
#50
b101 #
b101 %
b101 $
#60
b110 #
b110 %
b110 $
#70
b111 #
b111 %
b111 $
#80
b11 "
b11 &
b1000 #
b1000 %
b1000 $
#90
b1001 #
b1001 %
b1001 $
#100
b1010 #
b1010 %
b1010 $
#110
b1011 #
b1011 %
b1011 $
#120
b1100 #
b1100 %
b1100 $
#130
b1101 #
b1101 %
b1101 $
#140
b1110 #
b1110 %
b1110 $
#150
b1111 $
