dsd-lab/Week-5/Dump/Decoder4_16.v
module Decoder2_4(w, e, y);
  input [1:0] w;
  input e;
  output reg [0:3] y;

  always @(e, w)
  begin 
  y = 4'b0000;
    if (w == 2'b00 && e == 1)
      y[0] = 1;
    else if (w == 2'b01 && e == 1)
      y[1] = 1;
    else if (w == 2'b10 && e == 1)
      y[2] = 1;
    else if (w == 2'b11 && e == 1)
      y[3] = 1;
  end
endmodule

module Decoder4_16(w, e, y);
  input [3:0]w;
  input e;
  output [0:15]y;
  wire [0:3]m;

  Decoder2_4 D1(w[3:2], e, m[0:3]);
  Decoder2_4 D2(w[1:0], m[0], y[0:3]);
  Decoder2_4 D3(w[1:0], m[1], y[4:7]);
  Decoder2_4 D4(w[1:0], m[2], y[8:11]);
  Decoder2_4 D5(w[1:0], m[3], y[12:15]);
 endmodule

dsd-lab/Week-5/Dump/Decoder4_16_tb.v
`timescale 1ns/1ns
`include "Decoder4_16.v"

module Decoder4_16_tb;
  reg [3:0]w;   // 4-bit input
  reg e;
  wire [0:15]y;   


Decoder4_16 D2(w, e, y);
  // Initialize simulation
  initial begin
    $dumpfile("Decoder4_16_tb.vcd");
    $dumpvars(0, Decoder4_16_tb);

    // Test case 1: Select input 0
    e=1;
    w = 0;
    #20;

    // Test case 2: Select input 1
    e=1;
    w = 1;
    #20;

    // Test case 3: Select input 2
    e=1;
    w = 2;
    #20;

    // Test case 4: Select input 3
    e=1;
    w = 3;
    #20;
    
    //Don't care case
    e=1;
    w = 4;
    #20;
    
    e=1;
    w = 5;
    #20;
    
    e=1;
    w = 6;
    #20;
    
    e=1;
    w = 7;
    #20;
    
    e=1;
    w = 8;
    #20;
    
    e=1;
    w = 9;
    #20;
    
    e=1;
    w = 10;
    #20;
    
    e=1;
    w = 11;
    #20;
    
    e=1;
    w = 12;
    #20;

    e=1;
    w = 13;
    #20;
    
    e=1;
    w = 14;
    #20;
    
    e=1;
    w = 15;
    #20;
    
    e=0;
    w = 15;
    #20;
    
    $display("Test Complete");
    $finish; // End simulation
  end
endmodule

dsd-lab/Week-5/Dump/Decoder4_16_tb.vcd
$date
	Sun Aug 27 20:57:08 2023
$end
$version
	Icarus Verilog
$end
$timescale
	1ns
$end
$scope module Decoder4_16_tb $end
$var wire 16 ! y [0:15] $end
$var reg 1 " e $end
$var reg 4 # w [3:0] $end
$scope module D2 $end
$var wire 1 " e $end
$var wire 4 $ w [3:0] $end
$var wire 16 % y [0:15] $end
$var wire 4 & m [0:3] $end
$scope module D1 $end
$var wire 1 " e $end
$var wire 2 ' w [1:0] $end
$var reg 4 ( y [0:3] $end
$upscope $end
$scope module D2 $end
$var wire 1 ) e $end
$var wire 2 * w [1:0] $end
$var reg 4 + y [0:3] $end
$upscope $end
$scope module D3 $end
$var wire 1 , e $end
$var wire 2 - w [1:0] $end
$var reg 4 . y [0:3] $end
$upscope $end
$scope module D4 $end
$var wire 1 / e $end
$var wire 2 0 w [1:0] $end
$var reg 4 1 y [0:3] $end
$upscope $end
$scope module D5 $end
$var wire 1 2 e $end
$var wire 2 3 w [1:0] $end
$var reg 4 4 y [0:3] $end
$upscope $end
$upscope $end
$upscope $end
$enddefinitions $end
#0
$dumpvars
b0 4
b0 3
02
b0 1
b0 0
0/
b0 .
b0 -
0,
b1000 +
b0 *
1)
b1000 (
b0 '
b1000 &
b1000000000000000 %
b0 $
b0 #
1"
b1000000000000000 !
$end
#20
b100000000000000 !
b100000000000000 %
b100 +
b1 *
b1 -
b1 0
b1 3
b1 #
b1 $
#40
b10000000000000 !
b10000000000000 %
b10 +
b10 *
b10 -
b10 0
b10 3
b10 #
b10 $
#60
b1000000000000 !
b1000000000000 %
b1 +
b11 *
b11 -
b11 0
b11 3
b11 #
b11 $
#80
b1000 .
1,
0)
b100 &
b100 (
b100000000000 !
b100000000000 %
b0 +
b1 '
b0 *
b0 -
b0 0
b0 3
b100 #
b100 $
#100
b10000000000 !
b10000000000 %
b100 .
b1 *
b1 -
b1 0
b1 3
b101 #
b101 $
#120
b1000000000 !
b1000000000 %
b10 .
b10 *
b10 -
b10 0
b10 3
b110 #
b110 $
#140
b100000000 !
b100000000 %
b1 .
b11 *
b11 -
b11 0
b11 3
b111 #
b111 $
#160
b1000 1
1/
0,
b10 &
b10 (
b10000000 !
b10000000 %
b0 .
b10 '
b0 *
b0 -
b0 0
b0 3
b1000 #
b1000 $
#180
b1000000 !
b1000000 %
b100 1
b1 *
b1 -
b1 0
b1 3
b1001 #
b1001 $
#200
b100000 !
b100000 %
b10 1
b10 *
b10 -
b10 0
b10 3
b1010 #
b1010 $
#220
b10000 !
b10000 %
b1 1
b11 *
b11 -
b11 0
b11 3
b1011 #
b1011 $
#240
b1000 4
12
0/
b1 &
b1 (
b1000 !
b1000 %
b0 1
b11 '
b0 *
b0 -
b0 0
b0 3
b1100 #
b1100 $
#260
b100 !
b100 %
b100 4
b1 *
b1 -
b1 0
b1 3
b1101 #
b1101 $
#280
b10 !
b10 %
b10 4
b10 *
b10 -
b10 0
b10 3
b1110 #
b1110 $
#300
b1 !
b1 %
b1 4
b11 *
b11 -
b11 0
b11 3
b1111 #
b1111 $
#320
b0 !
b0 %
b0 4
02
b0 &
b0 (
0"
