dsd-lab/Lab-10/Q1/jkFlipFlop.v
module jkFlipFlop(j,k,reset,clk,Q);
input j,k,reset,clk;
output reg Q;

always@(reset)
begin
if(reset)
Q<=0;
end

always@(posedge clk)
begin
if(j==1&k==1)
Q<=(~Q);
else if(k==1)
Q<=0;
else if(j==1)
Q<=1;
end

endmodule

dsd-lab/Lab-10/Q1/Q1.v
`include "jkFlipFlop.v"
module Q1(clk,reset,V);
input clk,reset;
output [2:0]V;

jkFlipFlop jk1(V[1],(V[1]&V[0]),reset,clk,V[2]);
jkFlipFlop jk2(V[0],((~V[2])|V[0]),reset,clk,V[1]);
jkFlipFlop jk3((V[2]|(~V[1])),1'b1,reset,clk,V[0]);

endmodule

dsd-lab/Lab-10/Q1/Q1_tb.v
`timescale 1ns/1ns
`include "Q1.v"


module Q1_tb;
reg clk,reset;
wire [2:0]V;
Q1 Q(clk,reset,V);
always #10 clk=~clk;
initial begin
$dumpfile("Q1_tb.vcd");
$dumpvars(0,Q1_tb);
clk=0;
end
initial begin
reset=1'b1;#20;
reset=1'b0;#20;
reset=1'b0;#20;
reset=1'b0;#20;
reset=1'b0;#20;
reset=1'b0;#20;
reset=1'b0;#20;
reset=1'b0;#20;
reset=1'b0;#20;
reset=1'b0;#20;
$finish;
end
endmodule

dsd-lab/Lab-10/Q1/Q1_tb.vcd
$date
	Thu Nov  2 09:46:29 2023
$end
$version
	Icarus Verilog
$end
$timescale
	1ns
$end
$scope module Q1_tb $end
$var wire 3 ! V [2:0] $end
$var reg 1 " clk $end
$var reg 1 # reset $end
$scope module Q $end
$var wire 1 " clk $end
$var wire 1 # reset $end
$var wire 3 $ V [2:0] $end
$scope module jk1 $end
$var wire 1 " clk $end
$var wire 1 % j $end
$var wire 1 & k $end
$var wire 1 # reset $end
$var reg 1 ' Q $end
$upscope $end
$scope module jk2 $end
$var wire 1 " clk $end
$var wire 1 ( j $end
$var wire 1 ) k $end
$var wire 1 # reset $end
$var reg 1 * Q $end
$upscope $end
$scope module jk3 $end
$var wire 1 " clk $end
$var wire 1 + j $end
$var wire 1 , k $end
$var wire 1 # reset $end
$var reg 1 - Q $end
$upscope $end
$upscope $end
$upscope $end
$enddefinitions $end
#0
$dumpvars
0-
1,
1+
0*
1)
0(
0'
0&
0%
b0 $
1#
0"
b0 !
$end
#10
1(
b1 !
b1 $
1-
1"
#20
0"
0#
#30
0+
0(
1%
0-
b10 !
b10 $
1*
1"
#40
0"
#50
0)
1+
0%
1'
b100 !
b100 $
0*
1"
#60
0"
#70
1)
1(
b101 !
b101 $
1-
1"
#80
0"
#90
0)
1%
0(
1*
b110 !
b110 $
0-
1"
#100
0"
#110
1)
1&
1(
b111 !
b111 $
1-
1"
#120
0"
#130
1)
0&
0%
0(
0'
0*
b0 !
b0 $
0-
1"
#140
0"
#150
1(
b1 !
b1 $
1-
1"
#160
0"
#170
0+
1%
0(
1*
b10 !
b10 $
0-
1"
#180
0"
#190
0)
1+
0%
0*
b100 !
b100 $
1'
1"
