dsd-lab/Lab-9/Q3/q3.v
module TFF(t, clk, reset, q);
	input t, clk, reset;
	output reg q;
	always @(negedge clk)
	begin
		if (reset)
			q <= 0;
		else if (t)
			q <= ~q;
	end
endmodule

module q3(clk, reset, Q);
	input clk, reset;
	output [3:0]Q;
	TFF s0(1'b1, clk, reset, Q[0]);
	TFF s1(1'b1, Q[0], reset, Q[1]);
	TFF s2(1'b1, Q[1], reset, Q[2]);
	TFF s3(1'b1, Q[2], reset, Q[3]);
endmodule

dsd-lab/Lab-9/Q3/q3_tb.v
`timescale 1ns/1ns
`include "q3.v"

module q3_tb;

reg clk, reset;
wire [0:3]Q;

q3 h1(clk, reset, Q);

initial begin
	clk=0;
	forever #10 clk = ~clk;
end
initial begin
	$dumpfile("q3_tb.vcd");
	$dumpvars(0, q3_tb);
	reset=1; #20;
	reset=0; #320;
	$display("Test Completed");
	$finish;
end
endmodule

dsd-lab/Lab-9/Q3/q3_tb.vcd
$date
	Thu Oct 26 10:14:31 2023
$end
$version
	Icarus Verilog
$end
$timescale
	1ns
$end
$scope module q3_tb $end
$var wire 4 ! Q [0:3] $end
$var reg 1 " clk $end
$var reg 1 # reset $end
$scope module h1 $end
$var wire 1 " clk $end
$var wire 1 # reset $end
$var wire 4 $ Q [3:0] $end
$scope module s0 $end
$var wire 1 " clk $end
$var wire 1 # reset $end
$var wire 1 % t $end
$var reg 1 & q $end
$upscope $end
$scope module s1 $end
$var wire 1 ' clk $end
$var wire 1 # reset $end
$var wire 1 ( t $end
$var reg 1 ) q $end
$upscope $end
$scope module s2 $end
$var wire 1 * clk $end
$var wire 1 # reset $end
$var wire 1 + t $end
$var reg 1 , q $end
$upscope $end
$scope module s3 $end
$var wire 1 - clk $end
$var wire 1 # reset $end
$var wire 1 . t $end
$var reg 1 / q $end
$upscope $end
$upscope $end
$upscope $end
$enddefinitions $end
#0
$dumpvars
0/
1.
0-
0,
1+
0*
0)
1(
0'
0&
1%
b0 $
1#
0"
b0 !
$end
#10
1"
#20
1'
b1 !
b1 $
1&
0"
0#
#30
1"
#40
1*
1)
0'
b10 !
b10 $
0&
0"
#50
1"
#60
1'
b11 !
b11 $
1&
0"
#70
1"
#80
1-
1,
0*
0)
0'
b100 !
b100 $
0&
0"
#90
1"
#100
1'
b101 !
b101 $
1&
0"
#110
1"
#120
1*
1)
0'
b110 !
b110 $
0&
0"
#130
1"
#140
1'
b111 !
b111 $
1&
0"
#150
1"
#160
1/
0-
0,
0*
0)
0'
b1000 !
b1000 $
0&
0"
#170
1"
#180
1'
b1001 !
b1001 $
1&
0"
#190
1"
#200
1*
1)
0'
b1010 !
b1010 $
0&
0"
#210
1"
#220
1'
b1011 !
b1011 $
1&
0"
#230
1"
#240
1-
1,
0*
0)
0'
b1100 !
b1100 $
0&
0"
#250
1"
#260
1'
b1101 !
b1101 $
1&
0"
#270
1"
#280
1*
1)
0'
b1110 !
b1110 $
0&
0"
#290
1"
#300
1'
b1111 !
b1111 $
1&
0"
#310
1"
#320
0/
0-
0,
0*
0)
0'
b0 !
b0 $
0&
0"
#330
1"
#340
1'
b1 !
b1 $
1&
0"
